{"startPage":"MainPage","startTheme":"BuRTheme1","pages":{"MainPage":{"layout":"MyLayout","assignments":[{"areaId":"Logo","contentId":"LogoHeader","type":"Content","backColor":"rgba(149, 149, 149, 0.3)"},{"areaId":"AreaMain","contentId":"ContentMainPage","type":"Content","backColor":"rgba(149, 149, 149, 0.3)"},{"areaId":"AreaNav","contentId":"NavigationContent","type":"Content","backColor":"rgba(149, 149, 149, 0.3)"}]},"DocumentationPage":{"layout":"MyLayout","assignments":[{"areaId":"Logo","contentId":"LogoHeader","type":"Content","backColor":"rgba(149, 149, 149, 0.3)"},{"areaId":"AreaMain","contentId":"ContentDocumentation","type":"Content","backColor":"rgba(149, 149, 149, 0.3)"},{"areaId":"AreaNav","contentId":"NavigationContent","type":"Content","backColor":"rgba(149, 149, 149, 0.3)"}]},"VideoPage":{"layout":"MyLayout","assignments":[{"areaId":"Logo","contentId":"LogoHeader","type":"Content","backColor":"rgba(149, 149, 149, 0.3)"},{"areaId":"AreaMain","contentId":"ContentVideo","type":"Content","backColor":"rgba(149, 149, 149, 0.3)"},{"areaId":"AreaNav","contentId":"NavigationContent","type":"Content","backColor":"rgba(149, 149, 149, 0.3)"}]},"JogPage":{"layout":"MyLayout","assignments":[{"areaId":"Logo","contentId":"LogoHeader","type":"Content","backColor":"rgba(149, 149, 149, 0.3)"},{"areaId":"AreaMain","contentId":"ContentJog","type":"Content","backColor":"rgba(149, 149, 149, 0.3)"},{"areaId":"AreaNav","contentId":"NavigationContent","type":"Content","backColor":"rgba(149, 149, 149, 0.3)"}]}},"layouts":{"MyLayout":{"areas":{"AreaNav":{"height":60,"width":1280,"top":740,"left":0},"AreaMain":{"height":680,"width":1280,"top":60,"left":0},"Logo":{"height":60,"width":1280,"top":0,"left":0}},"width":600,"height":500}},"contents":{"LogoHeader":{"path":"/contents/mappView/LogoHeader.html","height":60,"width":1280},"ContentMainPage":{"path":"/contents/mappView/ContentMainPage.html","height":680,"width":1280},"NavigationContent":{"path":"/contents/mappView/NavigationContent.html","height":60,"width":1280},"ContentDocumentation":{"path":"/contents/mappView/ContentDocumentation.html","height":680,"width":1280},"ContentVideo":{"path":"/contents/mappView/ContentVideo.html","height":680,"width":1280},"ContentJog":{"path":"/contents/mappView/ContentJog.html","height":680,"width":1280}},"themes":["BuRTheme1"],"configurations":{"activityCount":false}}